Metadata-Version: 2.1
Name: MDAKit
Version: 1.0.0
Summary: A kit with lots of tools for Molecular dynamic simulation analysis.
Home-page: https://github.com/Aunity/MDAKit
Author: Maohua Yang
Author-email: maohuay@hotmail.com
License: UNKNOWN
Keywords: molecular dynamic,analysis
Platform: UNKNOWN
